[
  {
    "old_name": "(Sub Viet) Left-Handed.Girl.2025.2160p.NF.WEB-DL.DDP.5.1.Atmos.H.265-CHDWEB.mkv",
    "new_name": "(Sub Viet) Left-Handed.Girl.2025.2160p.NF.WEB-DL.DDP.5.1.Atmos.H.265-CHDWEB_vie.srt",
    "timestamp": "2025-12-01T01:33:59.876658",
    "signature": "16344443919_6556.800000_39_ara,chi,cze,dan,dut,eng,fil,fin,fre,ger,gre,heb,hrv,hun,ind,ita,jpn,kor,may,nob,pol,por,rum,spa,swe,tha,tur,ukr,vie",
    "category": "subtitle",
    "output_path": "D:\\Video\\Subtitles\\(Sub Viet) Left-Handed.Girl.2025.2160p.NF.WEB-DL.DDP.5.1.Atmos.H.265-CHDWEB_vie.srt",
    "language": "vie",
    "notes": null,
    "remote_path": "subtitles/20251201_013359_(Sub Viet) Left-Handed.Girl.2025.2160p.NF.WEB-DL.DDP.5.1.Atmos.H.265-CHDWEB_vie.srt"
  },
  {
    "old_name": "(Sub Viet) Left-Handed.Girl.2025.2160p.NF.WEB-DL.DDP.5.1.Atmos.H.265-CHDWEB.mkv",
    "new_name": "4K_CHI_Taiwan_(Sub Viet) Left-Handed.Girl.2025.2160p.NF.WEB-DL.DDP.5.1.Atmos.H.265-CHDWEB.mkv",
    "timestamp": "2025-12-01T01:34:02.407959",
    "signature": "16344443919_6556.800000_39_ara,chi,cze,dan,dut,eng,fil,fin,fre,ger,gre,heb,hrv,hun,ind,ita,jpn,kor,may,nob,pol,por,rum,spa,swe,tha,tur,ukr,vie",
    "category": "video",
    "output_path": "D:\\Video\\4K_CHI_Taiwan_(Sub Viet) Left-Handed.Girl.2025.2160p.NF.WEB-DL.DDP.5.1.Atmos.H.265-CHDWEB.mkv",
    "language": null,
    "notes": null
  },
  {
    "old_name": "Demon.Slayer.Kimetsu.no.Yaiba.Infinity.Castle.2025.V2.2160p.SDR.HDTC.JAPANESE.x264.ESub-HDHub4u.Ms-Vietsub.mkv",
    "new_name": "Demon.Slayer.Kimetsu.no.Yaiba.Infinity.Castle.2025.V2.2160p.SDR.HDTC.JAPANESE.x264.ESub-HDHub4u.Ms-V_vie.srt",
    "timestamp": "2025-12-01T01:35:12.379267",
    "signature": "13052950961_9261.976000_2_eng,vie",
    "category": "subtitle",
    "output_path": "D:\\Video\\Subtitles\\Demon.Slayer.Kimetsu.no.Yaiba.Infinity.Castle.2025.V2.2160p.SDR.HDTC.JAPANESE.x264.ESub-HDHub4u.Ms-V_vie.srt",
    "language": "vie",
    "notes": null,
    "remote_path": "subtitles/20251201_013512_Demon.Slayer.Kimetsu.no.Yaiba.Infinity.Castle.2025.V2.2160p.SDR.HDTC.JAPANESE.x264.ESub-HDHub4u.Ms-V_vie.srt"
  },
  {
    "old_name": "Demon.Slayer.Kimetsu.no.Yaiba.Infinity.Castle.2025.V2.2160p.SDR.HDTC.JAPANESE.x264.ESub-HDHub4u.Ms-Vietsub.mkv",
    "new_name": "4K_JPN_HDHub4u.Ms_Demon.Slayer.Kimetsu.no.Yaiba.Infinity.Castle.2025.V2.2160p.SDR.HDTC.JAPANESE.x264.ESub-HDHub4u.Ms-Vietsub.mkv",
    "timestamp": "2025-12-01T01:35:15.649551",
    "signature": "13052950961_9261.976000_2_eng,vie",
    "category": "video",
    "output_path": "D:\\Video\\4K_JPN_HDHub4u.Ms_Demon.Slayer.Kimetsu.no.Yaiba.Infinity.Castle.2025.V2.2160p.SDR.HDTC.JAPANESE.x264.ESub-HDHub4u.Ms-Vietsub.mkv",
    "language": null,
    "notes": null
  }
]